wayne_utils/__init__.py
wayne_utils/base_utils.py
wayne_utils/data_utils.py
wayne_utils/log_utils.py
wayne_utils/nlp_utils.py
wayne_utils-0.0.20.dist-info/METADATA
wayne_utils-0.0.20.dist-info/WHEEL
wayne_utils-0.0.20.dist-info/top_level.txt
wayne_utils-0.0.20.dist-info/RECORD
