Metadata-Version: 2.4
Name: wayne_utils
Version: 0.0.20
Summary: A collection of commonly used code
Home-page: https://github.com/jiangpw41/MyTool
Author: Peiwen Jiang (Wayne)
Author-email: wayne_roaming@163.com
Classifier: Programming Language :: Python :: 3
Classifier: License :: OSI Approved :: MIT License
Classifier: Operating System :: OS Independent
Requires-Python: >=3.6
Requires-Dist: redis
Requires-Dist: pandas
Requires-Dist: openpyxl
Requires-Dist: pyyaml
Requires-Dist: python-docx
Requires-Dist: docx
Dynamic: author
Dynamic: author-email
Dynamic: classifier
Dynamic: description
Dynamic: description-content-type
Dynamic: home-page
Dynamic: requires-dist
Dynamic: requires-python
Dynamic: summary
